llm_api/__init__.py
llm_api/api_object.py
llm_api/completion.py
llm_api/error.py
llm_api/llm_object.py
llm_api/response.py
llm_api/util.py
llm_api_python-0.0.2.dist-info/LICENSE
llm_api_python-0.0.2.dist-info/METADATA
llm_api_python-0.0.2.dist-info/WHEEL
llm_api_python-0.0.2.dist-info/RECORD
