Metadata-Version: 2.1
Name: llm-api-python
Version: 0.0.2
Summary: A python lib to call LLM API models.
Home-page: https://github.com/1b5d/llm-api-python
License: MIT
Author: 1b5d
Author-email: 8110504+1b5d@users.noreply.github.com
Requires-Python: >=3.8.1,<4.0.0
Classifier: License :: OSI Approved :: MIT License
Classifier: Programming Language :: Python :: 3
Classifier: Programming Language :: Python :: 3.9
Classifier: Programming Language :: Python :: 3.10
Classifier: Programming Language :: Python :: 3.11
Requires-Dist: aiohttp (>=3.8,<4.0)
Requires-Dist: requests (>=2.28,<3.0)
Project-URL: Repository, https://github.com/1b5d/llm-api-python
